tspf_stomp/__init__.py
tspf_stomp/stomp.py
tspf_util/__init__.py
tspf_util/generate.py
TSPatternFinding-0.0.2.dist-info/LICENSE.txt
TSPatternFinding-0.0.2.dist-info/METADATA
TSPatternFinding-0.0.2.dist-info/WHEEL
TSPatternFinding-0.0.2.dist-info/entry_points.txt
TSPatternFinding-0.0.2.dist-info/top_level.txt
TSPatternFinding-0.0.2.dist-info/RECORD
